<?xml version="1.0" encoding="utf-8"?>
<sequenceGraph>
    <operation name="o1" start = "0" end = "10">
        <child name="o9" ></child>
        <device name="d1" x = "1" y = "1"></device>        
    </operation>

     <operation name="o2" start = "0" end = "10">
        <child name="o9" ></child>
        <device name="d2" x = "1" y = "1"></device>        
    </operation>

    <operation name="o3" start = "0" end = "10">
        <child name="o10" ></child>
        <device name="d3" x = "1" y = "1"></device>        
    </operation>

     <operation name="o4" start = "0" end = "10">
        <child name="o10" ></child>
        <device name="d4" x = "1" y = "1"></device>        
    </operation>

    <operation name="o5" start = "0" end = "10">
        <child name="o11" ></child>
        <device name="d5" x = "1" y = "1"></device>        
    </operation>

     <operation name="o6" start = "0" end = "10">
        <child name="o11" ></child>
        <device name="d6" x = "1" y = "1"></device>        
    </operation>

    <operation name="o7" start = "0" end = "10">
        <child name="o12" ></child>
        <device name="d7" x = "1" y = "1"></device>        
    </operation>

     <operation name="o8" start = "0" end = "10">
        <child name="o12" ></child>
        <device name="d8" x = "1" y = "1"></device>        
    </operation>

     <operation name="o9" start = "20" end = "30">
        <child name="o13" ></child>
	<parent name = "o1"></child>
	<parent name = "o2"></child>
        <device name="d9" x = "1" y = "1"></device>        
    </operation>

     <operation name="o10" start = "20" end = "30">
        <child name="o13" ></child>
	<parent name = "o3"></child>
	<parent name = "o4"></child>
        <device name="d10" x = "1" y = "1"></device>        
    </operation>

         <operation name="o11" start = "20" end = "30">
        <child name="o14" ></child>
	<parent name = "o5"></child>
	<parent name = "o6"></child>
        <device name="d11" x = "1" y = "1"></device>        
    </operation>

     <operation name="o12" start = "20" end = "30">
        <child name="o14" ></child>
	<parent name = "o7"></child>
	<parent name = "o8"></child>
        <device name="d12" x = "1" y = "1"></device>        
    </operation>

         <operation name="o13" start = "40" end = "50">
        <child name="o15" ></child>
	<parent name = "o9"></child>
	<parent name = "o10"></child>
        <device name="d13" x = "1" y = "1"></device>        
    </operation>

     <operation name="o14" start = "40" end = "50">
        <child name="o15" ></child>
	<parent name = "o11"></child>
	<parent name = "o12"></child>
        <device name="d15" x = "1" y = "1"></device>        
    </operation>
    
     <operation name="o15" start = "60" end = "70">
	<parent name = "o13"></child>
	<parent name = "o14"></child>
        <device name="d15" x = "1" y = "1"></device>        
    </operation>

    <operation name="o101" start = "100" end = "110">
        <child name="o109" ></child>
        <device name="d101" x = "1" y = "1"></device>        
    </operation>

     <operation name="o102" start = "100" end = "110">
        <child name="o109" ></child>
        <device name="d102" x = "1" y = "1"></device>        
    </operation>

    <operation name="o103" start = "100" end = "110">
        <child name="o110" ></child>
        <device name="d103" x = "1" y = "1"></device>        
    </operation>

     <operation name="o104" start = "100" end = "110">
        <child name="o110" ></child>
        <device name="d104" x = "1" y = "1"></device>        
    </operation>

    <operation name="o105" start = "100" end = "110">
        <child name="o111" ></child>
        <device name="d105" x = "1" y = "1"></device>        
    </operation>

     <operation name="o106" start = "100" end = "110">
        <child name="o111" ></child>
        <device name="d106" x = "1" y = "1"></device>        
    </operation>

    <operation name="o107" start = "100" end = "110">
        <child name="o112" ></child>
        <device name="d107" x = "1" y = "1"></device>        
    </operation>

     <operation name="o108" start = "100" end = "110">
        <child name="o112" ></child>
        <device name="d108" x = "1" y = "1"></device>        
    </operation>

     <operation name="o109" start = "120" end = "130">
        <child name="o113" ></child>
	<parent name = "o101"></child>
	<parent name = "o102"></child>
        <device name="d109" x = "1" y = "1"></device>        
    </operation>

     <operation name="o110" start = "120" end = "130">
        <child name="o113" ></child>
	<parent name = "o103"></child>
	<parent name = "o104"></child>
        <device name="d110" x = "1" y = "1"></device>        
    </operation>

         <operation name="o111" start = "120" end = "130">
        <child name="o114" ></child>
	<parent name = "o105"></child>
	<parent name = "o106"></child>
        <device name="d111" x = "1" y = "1"></device>        
    </operation>

     <operation name="o112" start = "120" end = "130">
        <child name="o114" ></child>
	<parent name = "o107"></child>
	<parent name = "o108"></child>
        <device name="d112" x = "1" y = "1"></device>        
    </operation>

         <operation name="o113" start = "140" end = "150">
        <child name="o115" ></child>
	<parent name = "o109"></child>
	<parent name = "o110"></child>
        <device name="d113" x = "1" y = "1"></device>        
    </operation>

     <operation name="o114" start = "140" end = "150">
        <child name="o115" ></child>
	<parent name = "o111"></child>
	<parent name = "o112"></child>
        <device name="d115" x = "1" y = "1"></device>        
    </operation>
    
     <operation name="o115" start = "160" end = "170">
	<parent name = "o113"></child>
	<parent name = "o114"></child>
        <device name="d115" x = "1" y = "1"></device>        
    </operation>

    
   
    
    
  
</sequenceGraph>
